hellopypa/__init__.py
hellopypa/__main__.py
hellopypa/example.cfg
hellopypa/hellopypa.py
hellopypa/version.py
hellopypa-0.0.11.dist-info/LICENSE
hellopypa-0.0.11.dist-info/METADATA
hellopypa-0.0.11.dist-info/WHEEL
hellopypa-0.0.11.dist-info/entry_points.txt
hellopypa-0.0.11.dist-info/top_level.txt
hellopypa-0.0.11.dist-info/RECORD
