Metadata-Version: 2.1
Name: hellopypa
Version: 0.0.11
Summary: A sample Python package
Home-page: https://github.com/mittelholcz/hellopypa
Author: mittelholcz
License: UNKNOWN
Platform: UNKNOWN
Classifier: Programming Language :: Python :: 3
Classifier: License :: OSI Approved :: MIT License
Classifier: Operating System :: POSIX :: Linux
Requires-Python: >=3.6
